speechwidgets/__init__.py
speechwidgets/_frontend.py
speechwidgets/_version.py
speechwidgets/spectrogramplayer.py
speechwidgets/labextension/build_log.json
speechwidgets/labextension/package.json
speechwidgets/labextension/static/lib_index_js.7ead8a2e549efcb7218e.js
speechwidgets/labextension/static/lib_index_js.7ead8a2e549efcb7218e.js.map
speechwidgets/labextension/static/lib_plugin_js.b98a7ec9cab736d22dde.js
speechwidgets/labextension/static/lib_plugin_js.b98a7ec9cab736d22dde.js.map
speechwidgets/labextension/static/lib_widget_js.dddee57e33b324864382.js
speechwidgets/labextension/static/lib_widget_js.dddee57e33b324864382.js.map
speechwidgets/labextension/static/remoteEntry.05e119e4c1076b4cfadb.js
speechwidgets/labextension/static/remoteEntry.05e119e4c1076b4cfadb.js.map
speechwidgets/labextension/static/style.js
speechwidgets/labextension/static/vendors-node_modules_react-audio-spectrogram-player_dist_react-audio-spectrogram-player_es_js.a74b02492f6a0f9f8992.js
speechwidgets/labextension/static/vendors-node_modules_react-audio-spectrogram-player_dist_react-audio-spectrogram-player_es_js.a74b02492f6a0f9f8992.js.map
speechwidgets/nbextension/extension.js
speechwidgets/nbextension/index.js
speechwidgets/nbextension/index.js.LICENSE.txt
speechwidgets/nbextension/index.js.map
speechwidgets/tests/__init__.py
speechwidgets/tests/conftest.py
speechwidgets/tests/test_example.py
speechwidgets/tests/test_nbextension_path.py
speechwidgets-1.0.1.data/data/etc/jupyter/nbconfig/notebook.d/speechwidgets.json
speechwidgets-1.0.1.data/data/share/jupyter/labextensions/speechwidgets/build_log.json
speechwidgets-1.0.1.data/data/share/jupyter/labextensions/speechwidgets/install.json
speechwidgets-1.0.1.data/data/share/jupyter/labextensions/speechwidgets/package.json
speechwidgets-1.0.1.data/data/share/jupyter/labextensions/speechwidgets/static/lib_index_js.7ead8a2e549efcb7218e.js
speechwidgets-1.0.1.dist-info/LICENSE.txt
speechwidgets-1.0.1.dist-info/METADATA
speechwidgets-1.0.1.dist-info/WHEEL
speechwidgets-1.0.1.dist-info/top_level.txt
speechwidgets-1.0.1.dist-info/RECORD
