Metadata-Version: 2.1
Name: speechwidgets
Version: 1.0.1
Summary: A library with Jupyter widgets for speech processing
Home-page: https://github.com/nicolvisser/speechwidgets
Author: nicolvisser
Author-email: nicolvisser@yahoo.com
License: BSD
Keywords: Jupyter,Widgets,IPython
Platform: Linux
Platform: Mac OS X
Platform: Windows
Classifier: Intended Audience :: Developers
Classifier: Intended Audience :: Science/Research
Classifier: License :: OSI Approved :: BSD License
Classifier: Programming Language :: Python
Classifier: Programming Language :: Python :: 3
Classifier: Programming Language :: Python :: 3.4
Classifier: Programming Language :: Python :: 3.5
Classifier: Programming Language :: Python :: 3.6
Classifier: Programming Language :: Python :: 3.7
Classifier: Framework :: Jupyter
Requires-Python: >=3.6
License-File: LICENSE.txt
Requires-Dist: ipywidgets (>=7.0.0)
Requires-Dist: ipykernel (>=6.22.0)
Requires-Dist: jupyter-packaging (>=0.12.3)
Requires-Dist: librosa (>=0.8.0)
Requires-Dist: numpy (>=1.0.0)
Requires-Dist: pytest (>=7.2.2)
Requires-Dist: setuptools (>=67.6.0)
Requires-Dist: Sphinx (>=6.1.3)
Requires-Dist: sphinx-rtd-theme (>=1.2.0)
Requires-Dist: traitlets (>=5.9.0)
Requires-Dist: traittypes (>=0.2.1)
Provides-Extra: docs
Requires-Dist: jupyter-sphinx ; extra == 'docs'
Requires-Dist: nbsphinx ; extra == 'docs'
Requires-Dist: nbsphinx-link ; extra == 'docs'
Requires-Dist: pytest-check-links ; extra == 'docs'
Requires-Dist: pypandoc ; extra == 'docs'
Requires-Dist: recommonmark ; extra == 'docs'
Requires-Dist: sphinx (>=1.5) ; extra == 'docs'
Requires-Dist: sphinx-rtd-theme ; extra == 'docs'
Provides-Extra: examples
Provides-Extra: test
Requires-Dist: pytest (>=4.6) ; extra == 'test'
Requires-Dist: pytest-cov ; extra == 'test'
Requires-Dist: nbval ; extra == 'test'
